{
  "_class": "symbolInstance",
  "booleanOperation": -1,
  "clippingMaskMode": 0,
  "do_objectID": "5DEF1D92-A618-4C39-9C45-4F945D4AE175",
  "exportOptions": {
    "_class": "exportOptions",
    "do_objectID": "76A97862-CDD2-408C-A741-8E5950081BB6",
    "exportFormats": [
      {
        "_class": "exportFormat",
        "absoluteSize": 0,
        "fileFormat": "png",
        "name": "",
        "namingScheme": 0,
        "scale": 1,
        "visibleScaleType": 0
      }
    ],
    "includedLayerIds": [
    ],
    "layerOptions": 0,
    "shouldTrim": false
  },
  "frame": {
    "_class": "rect",
    "constrainProportions": true,
    "do_objectID": "763DCE3F-5878-4DAB-A507-D148317A37D1",
    "height": 100,
    "width": 100,
    "x": 150,
    "y": 0
  },
  "hasClippingMask": false,
  "horizontalSpacing": 0,
  "isFixedToViewport": false,
  "isFlippedHorizontal": false,
  "isFlippedVertical": false,
  "isLocked": false,
  "isVisible": true,
  "layerListExpandedType": 0,
  "name": "icon/employer-checkmark-circle",
  "nameIsFixed": false,
  "overrideValues": [
    {
      "_class": "overrideValue",
      "do_objectID": "23F111D8-3FEA-4F48-AE32-AEA7183242DE",
      "overrideName": "8B2C98DC-74CC-4FBD-BC15-6B86D3E23A1C_symbolID",
      "value": "39D82034-4426-4EBF-B848-A822A1E735AD"
    }
  ],
  "resizingConstraint": 9,
  "resizingType": 0,
  "rotation": 0,
  "scale": 1,
  "shouldBreakMaskChain": false,
  "style": {
    "_class": "style",
    "do_objectID": "9A05D0F1-0D3B-4197-B6E8-86C32D7F90EC",
    "endMarkerType": 0,
    "miterLimit": 10,
    "startMarkerType": 0,
    "windingRule": 1
  },
  "symbolID": "DEAA7D43-70A4-45B3-B5C1-7D077BE17F5D",
  "verticalSpacing": 0
}