{
  "_class": "symbolInstance",
  "booleanOperation": 0,
  "clippingMaskMode": 0,
  "do_objectID": "A3BF500D-3E8B-438D-8068-BF32F46E5172",
  "exportOptions": {
    "_class": "exportOptions",
    "do_objectID": "BEC3DBE8-C662-4E22-80D3-D4292D1CEBB2",
    "exportFormats": [
      {
        "_class": "exportFormat",
        "absoluteSize": 0,
        "fileFormat": "png",
        "name": "",
        "namingScheme": 0,
        "scale": 1,
        "visibleScaleType": 0
      }
    ],
    "includedLayerIds": [
    ],
    "layerOptions": 0,
    "shouldTrim": false
  },
  "frame": {
    "_class": "rect",
    "constrainProportions": false,
    "do_objectID": "2C5A9EE6-74FD-4EDE-9520-54EFFDCE0DFF",
    "height": 99.99999999999997,
    "width": 100,
    "x": 150,
    "y": 0
  },
  "hasClippingMask": false,
  "horizontalSpacing": 0,
  "isFixedToViewport": false,
  "isFlippedHorizontal": false,
  "isFlippedVertical": false,
  "isLocked": false,
  "isVisible": true,
  "layerListExpandedType": 0,
  "name": "icon/employer-arrow-down-outline",
  "nameIsFixed": false,
  "overrideValues": [
  ],
  "resizingConstraint": 63,
  "resizingType": 0,
  "rotation": 0,
  "scale": 1,
  "shouldBreakMaskChain": false,
  "style": {
    "_class": "style",
    "do_objectID": "0305C6A8-8312-4DB5-8D99-49960F5FE9ED",
    "endMarkerType": 0,
    "miterLimit": 10,
    "startMarkerType": 0,
    "windingRule": 1
  },
  "symbolID": "873E36A1-E5D3-4EAC-8D08-8341F039A59C",
  "verticalSpacing": 0
}