{
  "_class": "symbolInstance",
  "booleanOperation": -1,
  "clippingMaskMode": 0,
  "do_objectID": "58AA8BBE-AE27-475C-9BFE-87DDF3C3BB3C",
  "exportOptions": {
    "_class": "exportOptions",
    "do_objectID": "0FFB6152-B1E6-4AAF-9E87-4BC9CE4B987E",
    "exportFormats": [
    ],
    "includedLayerIds": [
    ],
    "layerOptions": 0,
    "shouldTrim": false
  },
  "frame": {
    "_class": "rect",
    "constrainProportions": false,
    "do_objectID": "F8F98656-B590-4DB6-AAC3-6125CD76DFF1",
    "height": 23,
    "width": 103,
    "x": 572,
    "y": 0
  },
  "hasClippingMask": false,
  "horizontalSpacing": 0,
  "isFixedToViewport": false,
  "isFlippedHorizontal": false,
  "isFlippedVertical": false,
  "isLocked": false,
  "isVisible": true,
  "layerListExpandedType": 0,
  "name": "dashboard/horizontaltab/employers/default",
  "nameIsFixed": false,
  "overrideValues": [
    {
      "_class": "overrideValue",
      "do_objectID": "62AED9FE-791B-4650-B7DE-511BFFF4F53B",
      "overrideName": "8E460811-B25E-43E7-9A38-DD7B77DC4AF1_stringValue",
      "value": "lorem ipsum"
    }
  ],
  "resizingConstraint": 63,
  "resizingType": 0,
  "rotation": 0,
  "scale": 1,
  "shouldBreakMaskChain": false,
  "style": {
    "_class": "style",
    "do_objectID": "53EE8A20-8C02-4412-B156-227A097F10E0",
    "endMarkerType": 0,
    "miterLimit": 10,
    "startMarkerType": 0,
    "windingRule": 1
  },
  "symbolID": "B9940BDC-1F39-47D8-AB11-7969382C114C",
  "verticalSpacing": 0
}