{
  "_class": "group",
  "booleanOperation": 0,
  "clippingMaskMode": 0,
  "do_objectID": "CFF968F6-F860-43C9-B927-780A6151C427",
  "exportOptions": {
    "_class": "exportOptions",
    "do_objectID": "17CD9A2F-4CF2-4BEC-9299-1473E7CC0115",
    "exportFormats": [
    ],
    "includedLayerIds": [
    ],
    "layerOptions": 0,
    "shouldTrim": false
  },
  "frame": {
    "_class": "rect",
    "constrainProportions": false,
    "do_objectID": "D25018C6-0C89-421F-8B44-75156FB4EE90",
    "height": 50,
    "width": 77,
    "x": 0,
    "y": 0
  },
  "hasClickThrough": false,
  "hasClippingMask": false,
  "isFixedToViewport": false,
  "isFlippedHorizontal": false,
  "isFlippedVertical": false,
  "isLocked": false,
  "isVisible": true,
  "layerListExpandedType": 2,
  "layers": [
    {
      "class": "symbolInstance",
      "id": "1D9FAD64-C423-40F1-BA42-E73C6E0D1D07"
    },
    {
      "class": "symbolInstance",
      "id": "380114C2-4D9E-4797-A799-A5C9197B68EB"
    }
  ],
  "name": "Group 6",
  "nameIsFixed": false,
  "resizingConstraint": 63,
  "resizingType": 0,
  "rotation": 0,
  "shouldBreakMaskChain": false,
  "style": {
    "_class": "style",
    "do_objectID": "5B90D799-D150-4E4F-A29B-D676651858FF",
    "endMarkerType": 0,
    "miterLimit": 10,
    "startMarkerType": 0,
    "windingRule": 1
  }
}