{
  "_class": "symbolInstance",
  "booleanOperation": 0,
  "clippingMaskMode": 0,
  "do_objectID": "8581FDDB-4585-4BEA-82AB-970964BEA2A9",
  "exportOptions": {
    "_class": "exportOptions",
    "do_objectID": "20FEC9BC-7636-4AB7-B683-3899F9487FD5",
    "exportFormats": [
    ],
    "includedLayerIds": [
    ],
    "layerOptions": 0,
    "shouldTrim": false
  },
  "frame": {
    "_class": "rect",
    "constrainProportions": false,
    "do_objectID": "FF57C5DE-F72A-44D8-9E16-15551B93875E",
    "height": 23,
    "width": 406,
    "x": 0,
    "y": 33
  },
  "hasClippingMask": false,
  "horizontalSpacing": 0,
  "isFixedToViewport": false,
  "isFlippedHorizontal": false,
  "isFlippedVertical": false,
  "isLocked": false,
  "isVisible": true,
  "layerListExpandedType": 0,
  "name": "Job Card/Desktop/Component/Salary-Data/1-line Copy",
  "nameIsFixed": false,
  "overrideValues": [
    {
      "_class": "overrideValue",
      "do_objectID": "DA2B8215-2909-41D9-BA49-CFFA311BE05D",
      "overrideName": "0328FBE0-E1DD-4E81-9F30-D3DDCAD80811_stringValue",
      "value": "Singapore"
    }
  ],
  "resizingConstraint": 11,
  "resizingType": 0,
  "rotation": 0,
  "scale": 1,
  "shouldBreakMaskChain": false,
  "style": {
    "_class": "style",
    "do_objectID": "5C155407-5BDC-4900-9A2F-791CA821F0E0",
    "endMarkerType": 0,
    "miterLimit": 10,
    "startMarkerType": 0,
    "windingRule": 1
  },
  "symbolID": "88CA64FE-507B-4899-A78D-257EAFC42554",
  "verticalSpacing": 0
}