{
  "_class": "symbolInstance",
  "booleanOperation": 0,
  "clippingMaskMode": 0,
  "do_objectID": "9E6F5EDF-0A25-4547-AAB5-01E82D2280CF",
  "exportOptions": {
    "_class": "exportOptions",
    "do_objectID": "82CF6041-7C1E-4584-AD13-4E53FE77829D",
    "exportFormats": [
    ],
    "includedLayerIds": [
    ],
    "layerOptions": 0,
    "shouldTrim": false
  },
  "frame": {
    "_class": "rect",
    "constrainProportions": false,
    "do_objectID": "2A947410-9B03-4DEB-BA95-BEBB0A19FE96",
    "height": 20,
    "width": 333,
    "x": 415,
    "y": 59
  },
  "hasClippingMask": false,
  "horizontalSpacing": 0,
  "isFixedToViewport": false,
  "isFlippedHorizontal": false,
  "isFlippedVertical": false,
  "isLocked": false,
  "isVisible": true,
  "layerListExpandedType": 0,
  "name": "filter/location-company-noresults",
  "nameIsFixed": false,
  "overrideValues": [
  ],
  "resizingConstraint": 63,
  "resizingType": 0,
  "rotation": 0,
  "scale": 1,
  "shouldBreakMaskChain": false,
  "style": {
    "_class": "style",
    "do_objectID": "3A289C83-3920-4889-8A02-C0DDF9B7AF2F",
    "endMarkerType": 0,
    "miterLimit": 10,
    "startMarkerType": 0,
    "windingRule": 1
  },
  "symbolID": "907F5D35-97A9-4A63-8B5C-CDA77FD4BDA5",
  "verticalSpacing": 0
}