{
  "_class": "group",
  "booleanOperation": 0,
  "clippingMaskMode": 0,
  "do_objectID": "5B08A6A9-AEF7-4C45-82D1-99BFAAB2656D",
  "exportOptions": {
    "_class": "exportOptions",
    "do_objectID": "9E225889-09C9-4693-B8A6-8B9D705F4F85",
    "exportFormats": [
    ],
    "includedLayerIds": [
    ],
    "layerOptions": 0,
    "shouldTrim": false
  },
  "frame": {
    "_class": "rect",
    "constrainProportions": false,
    "do_objectID": "8E3FD3E7-4531-44AF-B957-0B905EFDFBAF",
    "height": 99,
    "width": 270,
    "x": 15,
    "y": 44
  },
  "hasClickThrough": false,
  "hasClippingMask": false,
  "isFixedToViewport": false,
  "isFlippedHorizontal": false,
  "isFlippedVertical": false,
  "isLocked": false,
  "isVisible": true,
  "layerListExpandedType": 1,
  "layers": [
    {
      "class": "group",
      "id": "E413FFAD-60AC-41F4-88F0-EDC12447AB13"
    }
  ],
  "name": "career",
  "nameIsFixed": true,
  "resizingConstraint": 63,
  "resizingType": 0,
  "rotation": 0,
  "shouldBreakMaskChain": false,
  "style": {
    "_class": "style",
    "do_objectID": "3A696F42-4C17-47AF-A906-02C8373B2600",
    "endMarkerType": 0,
    "miterLimit": 10,
    "startMarkerType": 0,
    "windingRule": 1
  }
}