{
  "_class": "symbolInstance",
  "booleanOperation": 0,
  "clippingMaskMode": 0,
  "do_objectID": "7B9ABE8D-F494-47F4-BBE6-56F3D30896F1",
  "exportOptions": {
    "_class": "exportOptions",
    "do_objectID": "BD7E9B09-313D-40A2-9945-C73639259820",
    "exportFormats": [
      {
        "_class": "exportFormat",
        "absoluteSize": 0,
        "fileFormat": "png",
        "name": "",
        "namingScheme": 0,
        "scale": 1,
        "visibleScaleType": 0
      }
    ],
    "includedLayerIds": [
    ],
    "layerOptions": 0,
    "shouldTrim": false
  },
  "frame": {
    "_class": "rect",
    "constrainProportions": false,
    "do_objectID": "59F9A3BF-EDC5-4290-8A7A-552331DC0D89",
    "height": 99.99999999999997,
    "width": 100,
    "x": 150,
    "y": 0
  },
  "hasClippingMask": false,
  "horizontalSpacing": 0,
  "isFixedToViewport": false,
  "isFlippedHorizontal": false,
  "isFlippedVertical": false,
  "isLocked": false,
  "isVisible": true,
  "layerListExpandedType": 0,
  "name": "icon/candidate-clock",
  "nameIsFixed": false,
  "overrideValues": [
    {
      "_class": "overrideValue",
      "do_objectID": "60F51C3E-A77A-4A4E-B9F5-5676BF958599",
      "overrideName": "6858C95E-FEDC-49CF-BA52-1F61B64EA194_symbolID",
      "value": ""
    }
  ],
  "resizingConstraint": 63,
  "resizingType": 0,
  "rotation": 0,
  "scale": 1,
  "shouldBreakMaskChain": false,
  "style": {
    "_class": "style",
    "do_objectID": "464AE67F-CB2D-404E-8807-E0659B16F8A3",
    "endMarkerType": 0,
    "miterLimit": 10,
    "startMarkerType": 0,
    "windingRule": 1
  },
  "symbolID": "1A48A2E9-67AF-4266-9DC1-C585116987E3",
  "verticalSpacing": 0
}