{
  "_class": "group",
  "booleanOperation": 0,
  "clippingMaskMode": 0,
  "do_objectID": "BE0859C2-43B9-48BE-96E3-BCA175C13EA8",
  "exportOptions": {
    "_class": "exportOptions",
    "do_objectID": "955EF01E-D37B-4B21-BF56-1F4851EDA45A",
    "exportFormats": [
    ],
    "includedLayerIds": [
    ],
    "layerOptions": 0,
    "shouldTrim": false
  },
  "frame": {
    "_class": "rect",
    "constrainProportions": false,
    "do_objectID": "B5550A86-5EF5-4E78-9E68-D762A87AB5BF",
    "height": 26,
    "width": 42,
    "x": 30,
    "y": 15
  },
  "hasClickThrough": false,
  "hasClippingMask": false,
  "isFixedToViewport": false,
  "isFlippedHorizontal": false,
  "isFlippedVertical": false,
  "isLocked": false,
  "isVisible": true,
  "layerListExpandedType": 2,
  "layers": [
    {
      "class": "text",
      "id": "C29FC1F8-0217-4354-B3C8-8AADB25B9673"
    }
  ],
  "name": "Group",
  "nameIsFixed": false,
  "resizingConstraint": 63,
  "resizingType": 0,
  "rotation": 0,
  "shouldBreakMaskChain": false,
  "style": {
    "_class": "style",
    "do_objectID": "FBFD1F94-1D12-43CA-88AA-DC3FD5CF4D23",
    "endMarkerType": 0,
    "miterLimit": 10,
    "startMarkerType": 0,
    "windingRule": 1
  }
}