{
  "_class": "text",
  "attributedString": {
    "_class": "attributedString",
    "attributes": [
      {
        "_class": "stringAttribute",
        "attributes": {
          "MSAttributedStringColorAttribute": {
            "_class": "color",
            "alpha": 1,
            "blue": 0,
            "green": 0,
            "red": 0
          },
          "MSAttributedStringFontAttribute": {
            "_class": "fontDescriptor",
            "attributes": {
              "name": "Poppins-Bold",
              "size": 26
            }
          },
          "paragraphStyle": {
            "_class": "paragraphStyle",
            "alignment": 0,
            "maximumLineHeight": 36.40000152587891,
            "minimumLineHeight": 36.40000152587891
          }
        },
        "length": 8,
        "location": 0
      }
    ],
    "string": "Expanded"
  },
  "automaticallyDrawOnUnderlyingPath": false,
  "booleanOperation": 0,
  "clippingMaskMode": 0,
  "do_objectID": "4EC733BF-1AA4-4CBA-AB47-29EC0E4DA2D3",
  "dontSynchroniseWithSymbol": false,
  "exportOptions": {
    "_class": "exportOptions",
    "do_objectID": "D7A8D594-DF22-4C26-81FA-A15887A7473E",
    "exportFormats": [
    ],
    "includedLayerIds": [
    ],
    "layerOptions": 0,
    "shouldTrim": false
  },
  "frame": {
    "_class": "rect",
    "constrainProportions": false,
    "height": 37,
    "width": 137,
    "x": 1243,
    "y": 200.5999984741211
  },
  "glyphBounds": "{{1, 11}, {132, 27}}",
  "hasClippingMask": false,
  "isFixedToViewport": false,
  "isFlippedHorizontal": false,
  "isFlippedVertical": false,
  "isLocked": false,
  "isVisible": true,
  "layerListExpandedType": 0,
  "lineSpacingBehaviour": 2,
  "name": "Expanded",
  "nameIsFixed": false,
  "resizingConstraint": 47,
  "resizingType": 0,
  "rotation": 0,
  "sharedStyleID": "54FB75CA-AF8E-46AC-9183-5287AF59A379",
  "shouldBreakMaskChain": false,
  "style": {
    "_class": "style",
    "do_objectID": "4EAACAE0-CA60-4DD7-8F64-908189F5024B",
    "endMarkerType": 0,
    "miterLimit": 10,
    "startMarkerType": 0,
    "textStyle": {
      "_class": "textStyle",
      "encodedAttributes": {
        "MSAttributedStringColorAttribute": {
          "_class": "color",
          "alpha": 1,
          "blue": 0,
          "green": 0,
          "red": 0
        },
        "MSAttributedStringFontAttribute": {
          "_class": "fontDescriptor",
          "attributes": {
            "name": "Poppins-Bold",
            "size": 26
          }
        },
        "paragraphStyle": {
          "_class": "paragraphStyle",
          "alignment": 0,
          "maximumLineHeight": 36.40000152587891,
          "minimumLineHeight": 36.40000152587891
        }
      },
      "verticalAlignment": 0
    },
    "windingRule": 1
  },
  "textBehaviour": 0
}