{
  "_class": "symbolMaster",
  "backgroundColor": {
    "_class": "color",
    "alpha": 1,
    "blue": 1,
    "green": 1,
    "red": 1
  },
  "booleanOperation": 0,
  "changeIdentifier": 14,
  "clippingMaskMode": 0,
  "do_objectID": "4B724816-5A23-4E98-811E-CE5D6D9E7DA4",
  "exportOptions": {
    "_class": "exportOptions",
    "exportFormats": [
    ],
    "includedLayerIds": [
    ],
    "layerOptions": 0,
    "shouldTrim": false
  },
  "frame": {
    "_class": "rect",
    "constrainProportions": false,
    "height": 4,
    "width": 70,
    "x": 44316,
    "y": -1172
  },
  "hasBackgroundColor": false,
  "hasClickThrough": true,
  "hasClippingMask": false,
  "horizontalRulerData": {
    "_class": "rulerData",
    "base": 0,
    "guides": [
    ]
  },
  "includeBackgroundColorInExport": true,
  "includeBackgroundColorInInstance": false,
  "includeInCloudUpload": true,
  "isFixedToViewport": false,
  "isFlippedHorizontal": false,
  "isFlippedVertical": false,
  "isFlowHome": false,
  "isLocked": false,
  "isVisible": true,
  "layerListExpandedType": 0,
  "layers": [
    {
      "class": "rectangle",
      "id": "6C990A47-BD80-4285-9552-CF0D0F0E8D5E"
    },
    {
      "class": "symbolInstance",
      "id": "2104F696-7AA0-40D5-9E1B-60C6EDECCD1E"
    }
  ],
  "name": "Divider",
  "nameIsFixed": true,
  "resizesContent": false,
  "resizingConstraint": 63,
  "resizingType": 0,
  "rotation": 0,
  "shouldBreakMaskChain": true,
  "style": {
    "_class": "style",
    "endMarkerType": 0,
    "miterLimit": 10,
    "startMarkerType": 0,
    "windingRule": 1
  },
  "symbolID": "4A87AC55-77AD-47F4-AE88-03EBEFE77B1B",
  "verticalRulerData": {
    "_class": "rulerData",
    "base": 0,
    "guides": [
    ]
  }
}